rss/__init__.py
rss/api.py
rss/client.py
rss/forge_api.py
rss/forge_client.py
rss/tests/__init__.py
rss/tests/test_api.py
real_simple_seismic-0.0.3.dist-info/METADATA
real_simple_seismic-0.0.3.dist-info/WHEEL
real_simple_seismic-0.0.3.dist-info/top_level.txt
real_simple_seismic-0.0.3.dist-info/RECORD
