Metadata-Version: 2.1
Name: real-simple-seismic
Version: 0.0.3
Summary: real simple seismic
Home-page: UNKNOWN
License: UNKNOWN
Platform: UNKNOWN
Classifier: Development Status :: 3 - Alpha
Classifier: Intended Audience :: Science/Research
Classifier: License :: OSI Approved :: Apache Software License
Classifier: Programming Language :: Python :: 3.6
Requires-Python: >=3.7
Requires-Dist: numpy
Requires-Dist: ebcdic
Requires-Dist: ibm2ieee
Requires-Dist: tqdm
Requires-Dist: numcodecs
Requires-Dist: s3fs
Requires-Dist: scipy
Requires-Dist: zarr
